pygit/__init__.py
pygit/cli.py
pygit/core/__init__.py
pygit/core/branch.py
pygit/core/commit.py
pygit/core/diff.py
pygit/core/merge.py
pygit/core/objects.py
pygit/core/remote.py
pygit/core/repository.py
pygit_lite-0.1.0.dist-info/METADATA
pygit_lite-0.1.0.dist-info/WHEEL
pygit_lite-0.1.0.dist-info/entry_points.txt
pygit_lite-0.1.0.dist-info/top_level.txt
pygit_lite-0.1.0.dist-info/RECORD
