Metadata-Version: 2.2
Name: pygit-lite
Version: 0.1.0
Summary: A Python implementation of Git
Home-page: https://github.com/aaniset/pygit
Author: Anudeep
Author-email: aaniset1@asu.edu
Classifier: Programming Language :: Python :: 3
Classifier: License :: OSI Approved :: MIT License
Classifier: Operating System :: OS Independent
Requires-Python: >=3.6
Dynamic: author
Dynamic: author-email
Dynamic: classifier
Dynamic: description-content-type
Dynamic: home-page
Dynamic: requires-python
Dynamic: summary
